izihawa_textparser/__init__.py
izihawa_textparser/_banned_sections.py
izihawa_textparser/_epub.py
izihawa_textparser/_grobid.py
izihawa_textparser/_pubmed.py
izihawa_textparser/utils.py
izihawa_textparser-0.2.50.dist-info/METADATA
izihawa_textparser-0.2.50.dist-info/WHEEL
izihawa_textparser-0.2.50.dist-info/RECORD
